networking_sfc/__init__.py
networking_sfc/_i18n.py
networking_sfc/opts.py
networking_sfc/version.py
networking_sfc/db/__init__.py
networking_sfc/db/flowclassifier_db.py
networking_sfc/db/sfc_db.py
networking_sfc/db/migration/README
networking_sfc/db/migration/__init__.py
networking_sfc/db/migration/alembic_migrations/__init__.py
networking_sfc/db/migration/alembic_migrations/env.py
networking_sfc/db/migration/alembic_migrations/script.py.mako
networking_sfc/db/migration/alembic_migrations/versions/CONTRACT_HEAD
networking_sfc/db/migration/alembic_migrations/versions/EXPAND_HEAD
networking_sfc/db/migration/alembic_migrations/versions/start_networking_sfc.py
networking_sfc/db/migration/alembic_migrations/versions/mitaka/contract/48072cb59133_initial.py
networking_sfc/db/migration/alembic_migrations/versions/mitaka/expand/24fc7241aa5_initial.py
networking_sfc/db/migration/alembic_migrations/versions/mitaka/expand/5a475fc853e6_ovs_data_model.py
networking_sfc/db/migration/alembic_migrations/versions/mitaka/expand/9768e6a66c9_flowclassifier_data_model.py
networking_sfc/db/migration/alembic_migrations/versions/mitaka/expand/c3e178d4a985_sfc_data_model.py
networking_sfc/db/migration/alembic_migrations/versions/mitaka/expand/d1002a1f97f6_update_flow_classifier.py
networking_sfc/db/migration/alembic_migrations/versions/mitaka/expand/fa75d46a7f11_add_port_pair_group_params.py
networking_sfc/db/migration/alembic_migrations/versions/newton/contract/010308b06b49_rename_tenant_to_project.py
networking_sfc/db/migration/alembic_migrations/versions/newton/contract/06382790fb2c_fix_foreign_constraints.py
networking_sfc/db/migration/alembic_migrations/versions/ocata/expand/6185f1633a3d_add_correlation_as_pp_detail.py
networking_sfc/db/migration/alembic_migrations/versions/ocata/expand/b3adaf631bab__add_fwd_path_and_in_mac_column.py
networking_sfc/db/migration/alembic_migrations/versions/pike/expand/61832141fb82_add_ppg_n_tuple_mapping_column.py
networking_sfc-21.0.0.dist-info/AUTHORS
networking_sfc-21.0.0.dist-info/LICENSE
networking_sfc-21.0.0.dist-info/METADATA
networking_sfc-21.0.0.dist-info/WHEEL
networking_sfc-21.0.0.dist-info/entry_points.txt
networking_sfc-21.0.0.dist-info/pbr.json
networking_sfc-21.0.0.dist-info/top_level.txt
networking_sfc-21.0.0.dist-info/RECORD
