Metadata-Version: 2.1
Name: networking-sfc
Version: 21.0.0
Summary: APIs and implementations to support Service Function Chaining in Neutron.
Home-page: https://docs.openstack.org/networking-sfc/latest/
Author: OpenStack
Author-email: openstack-discuss@lists.openstack.org
Classifier: Environment :: OpenStack
Classifier: Intended Audience :: Information Technology
Classifier: Intended Audience :: System Administrators
Classifier: License :: OSI Approved :: Apache Software License
Classifier: Operating System :: POSIX :: Linux
Classifier: Programming Language :: Python
Classifier: Programming Language :: Python :: Implementation :: CPython
Classifier: Programming Language :: Python :: 3 :: Only
Classifier: Programming Language :: Python :: 3
Classifier: Programming Language :: Python :: 3.10
Classifier: Programming Language :: Python :: 3.11
Classifier: Programming Language :: Python :: 3.12
Requires-Python: >=3.10
License-File: LICENSE
License-File: AUTHORS
Requires-Dist: pbr >=4.0.0
Requires-Dist: netaddr >=0.7.18
Requires-Dist: python-neutronclient >=10.0.0
Requires-Dist: SQLAlchemy >=2.0.0
Requires-Dist: alembic >=0.9.6
Requires-Dist: stevedore >=1.20.0
Requires-Dist: oslo.config >=8.0.0
Requires-Dist: oslo.i18n >=3.20.0
Requires-Dist: oslo.log >=4.3.0
Requires-Dist: oslo.messaging >=12.4.0
Requires-Dist: oslo.serialization >=2.25.0
Requires-Dist: oslo.utils >=4.5.0
Requires-Dist: neutron-lib >=2.19.0
Requires-Dist: neutron >=27.0.0.0b1
